Metadata-Version: 2.1
Name: npdtoolsfix
Version: 1.0
Summary: Удобный инструмент для взаимодействия с НПД (небольшие изменения оригинальной библиотеки npdtools, чтобы она работала с физ лицами без багов)
Author-email: xmaxer3@yandex.ru
License: UNKNOWN
Platform: UNKNOWN
